dagpiler/__init__.py
dagpiler/__main__.py
dagpiler/config_reader.py
dagpiler/constants.py
dagpiler/core.py
dagpiler/init.py
dagpiler/read_and_compile_dag.py
dagpiler/bridges/bridges.py
dagpiler/dag/furcate.py
dagpiler/dag/organizer.py
dagpiler/dag/package_runnables.py
dagpiler/dag/plot_dag.py
dagpiler/dag/printer.py
dagpiler/index/index_parser.py
dagpiler/index/index_processor.py
dagpiler/nodes/__init__.py
dagpiler/nodes/node.py
dagpiler/nodes/runnables/__init__.py
dagpiler/nodes/runnables/dict_attr_validator.py
dagpiler/nodes/runnables/dict_cleaner.py
dagpiler/nodes/runnables/dict_validator.py
dagpiler/nodes/runnables/plot.py
dagpiler/nodes/runnables/process.py
dagpiler/nodes/runnables/runnable_factory.py
dagpiler/nodes/runnables/runnables.py
dagpiler/nodes/variables/variable_factory.py
dagpiler/nodes/variables/variables.py
dagpiler-0.1.6.dist-info/METADATA
dagpiler-0.1.6.dist-info/WHEEL
dagpiler-0.1.6.dist-info/entry_points.txt
dagpiler-0.1.6.dist-info/licenses/LICENSE
dagpiler-0.1.6.dist-info/RECORD
