Metadata-Version: 2.3
Name: dagpiler
Version: 0.1.6
Summary: Compile a DAG representation of a data processing pipeline from TOML files.
Project-URL: Homepage, https://github.com/ResearchOS/dagpiler
Project-URL: Documentation, https://researchos.github.io/dagpiler/
Project-URL: Repository, https://github.com/ResearchOS/dagpiler
Project-URL: Issues, https://github.com/ResearchOS/dagpiler/issues
Author-email: Mitchell Tillman <mtillman14@gmail.com>
License: GNU GENERAL PUBLIC LICENSE
License-File: LICENSE
Classifier: Development Status :: 3 - Alpha
Classifier: Intended Audience :: Developers
Classifier: Operating System :: OS Independent
Classifier: Programming Language :: Python :: 3
Classifier: Topic :: Software Development :: Build Tools
Requires-Dist: base-dag
Requires-Dist: mkdocs-awesome-pages-plugin
Requires-Dist: mkdocs-git-revision-date-localized-plugin
Requires-Dist: mkdocs-material
Requires-Dist: mkdocstrings
Requires-Dist: pyyaml
Requires-Dist: requests
Requires-Dist: toml
